{"nodes": [{"id": "c_users_vishalgoswami_eclipse_workspace_sunny_printers_src_main_java_repository_clientrepository_java", "label": "ClientRepository.java", "file_type": "code", "source_file": "C:\\Users\\VishalGoswami\\eclipse-workspace\\Sunny_Printers\\src\\main\\java\\repository\\ClientRepository.java", "source_location": "L1"}, {"id": "repository_clientrepository_clientrepository", "label": "ClientRepository", "file_type": "code", "source_file": "C:\\Users\\VishalGoswami\\eclipse-workspace\\Sunny_Printers\\src\\main\\java\\repository\\ClientRepository.java", "source_location": "L13"}, {"id": "repository_clientrepository_clientrepository_save", "label": ".save()", "file_type": "code", "source_file": "C:\\Users\\VishalGoswami\\eclipse-workspace\\Sunny_Printers\\src\\main\\java\\repository\\ClientRepository.java", "source_location": "L16"}, {"id": "repository_clientrepository_clientrepository_findallsortedbyid", "label": ".findAllSortedById()", "file_type": "code", "source_file": "C:\\Users\\VishalGoswami\\eclipse-workspace\\Sunny_Printers\\src\\main\\java\\repository\\ClientRepository.java", "source_location": "L45"}, {"id": "repository_clientrepository_clientrepository_findallwithuninvoicedcompletedjobs", "label": ".findAllWithUninvoicedCompletedJobs()", "file_type": "code", "source_file": "C:\\Users\\VishalGoswami\\eclipse-workspace\\Sunny_Printers\\src\\main\\java\\repository\\ClientRepository.java", "source_location": "L74"}, {"id": "repository_clientrepository_clientrepository_search", "label": ".search()", "file_type": "code", "source_file": "C:\\Users\\VishalGoswami\\eclipse-workspace\\Sunny_Printers\\src\\main\\java\\repository\\ClientRepository.java", "source_location": "L101"}, {"id": "repository_clientrepository_clientrepository_deletebyid", "label": ".deleteById()", "file_type": "code", "source_file": "C:\\Users\\VishalGoswami\\eclipse-workspace\\Sunny_Printers\\src\\main\\java\\repository\\ClientRepository.java", "source_location": "L138"}, {"id": "repository_clientrepository_clientrepository_openeditclient", "label": ".openEditClient()", "file_type": "code", "source_file": "C:\\Users\\VishalGoswami\\eclipse-workspace\\Sunny_Printers\\src\\main\\java\\repository\\ClientRepository.java", "source_location": "L155"}, {"id": "repository_clientrepository_clientrepository_update", "label": ".update()", "file_type": "code", "source_file": "C:\\Users\\VishalGoswami\\eclipse-workspace\\Sunny_Printers\\src\\main\\java\\repository\\ClientRepository.java", "source_location": "L161"}], "edges": [{"source": "c_users_vishalgoswami_eclipse_workspace_sunny_printers_src_main_java_repository_clientrepository_java", "target": "connection", "relation": "imports", "confidence": "EXTRACTED", "source_file": "C:\\Users\\VishalGoswami\\eclipse-workspace\\Sunny_Printers\\src\\main\\java\\repository\\ClientRepository.java", "source_location": "L3", "weight": 1.0}, {"source": "c_users_vishalgoswami_eclipse_workspace_sunny_printers_src_main_java_repository_clientrepository_java", "target": "preparedstatement", "relation": "imports", "confidence": "EXTRACTED", "source_file": "C:\\Users\\VishalGoswami\\eclipse-workspace\\Sunny_Printers\\src\\main\\java\\repository\\ClientRepository.java", "source_location": "L4", "weight": 1.0}, {"source": "c_users_vishalgoswami_eclipse_workspace_sunny_printers_src_main_java_repository_clientrepository_java", "target": "resultset", "relation": "imports", "confidence": "EXTRACTED", "source_file": "C:\\Users\\VishalGoswami\\eclipse-workspace\\Sunny_Printers\\src\\main\\java\\repository\\ClientRepository.java", "source_location": "L5", "weight": 1.0}, {"source": "c_users_vishalgoswami_eclipse_workspace_sunny_printers_src_main_java_repository_clientrepository_java", "target": "sqlexception", "relation": "imports", "confidence": "EXTRACTED", "source_file": "C:\\Users\\VishalGoswami\\eclipse-workspace\\Sunny_Printers\\src\\main\\java\\repository\\ClientRepository.java", "source_location": "L6", "weight": 1.0}, {"source": "c_users_vishalgoswami_eclipse_workspace_sunny_printers_src_main_java_repository_clientrepository_java", "target": "arraylist", "relation": "imports", "confidence": "EXTRACTED", "source_file": "C:\\Users\\VishalGoswami\\eclipse-workspace\\Sunny_Printers\\src\\main\\java\\repository\\ClientRepository.java", "source_location": "L7", "weight": 1.0}, {"source": "c_users_vishalgoswami_eclipse_workspace_sunny_printers_src_main_java_repository_clientrepository_java", "target": "list", "relation": "imports", "confidence": "EXTRACTED", "source_file": "C:\\Users\\VishalGoswami\\eclipse-workspace\\Sunny_Printers\\src\\main\\java\\repository\\ClientRepository.java", "source_location": "L8", "weight": 1.0}, {"source": "c_users_vishalgoswami_eclipse_workspace_sunny_printers_src_main_java_repository_clientrepository_java", "target": "client", "relation": "imports", "confidence": "EXTRACTED", "source_file": "C:\\Users\\VishalGoswami\\eclipse-workspace\\Sunny_Printers\\src\\main\\java\\repository\\ClientRepository.java", "source_location": "L10", "weight": 1.0}, {"source": "c_users_vishalgoswami_eclipse_workspace_sunny_printers_src_main_java_repository_clientrepository_java", "target": "dbconnection", "relation": "imports", "confidence": "EXTRACTED", "source_file": "C:\\Users\\VishalGoswami\\eclipse-workspace\\Sunny_Printers\\src\\main\\java\\repository\\ClientRepository.java", "source_location": "L11", "weight": 1.0}, {"source": "c_users_vishalgoswami_eclipse_workspace_sunny_printers_src_main_java_repository_clientrepository_java", "target": "repository_clientrepository_clientrepository", "relation": "contains", "confidence": "EXTRACTED", "source_file": "C:\\Users\\VishalGoswami\\eclipse-workspace\\Sunny_Printers\\src\\main\\java\\repository\\ClientRepository.java", "source_location": "L13", "weight": 1.0}, {"source": "repository_clientrepository_clientrepository", "target": "repository_clientrepository_clientrepository_save", "relation": "method", "confidence": "EXTRACTED", "source_file": "C:\\Users\\VishalGoswami\\eclipse-workspace\\Sunny_Printers\\src\\main\\java\\repository\\ClientRepository.java", "source_location": "L16", "weight": 1.0}, {"source": "repository_clientrepository_clientrepository", "target": "repository_clientrepository_clientrepository_findallsortedbyid", "relation": "method", "confidence": "EXTRACTED", "source_file": "C:\\Users\\VishalGoswami\\eclipse-workspace\\Sunny_Printers\\src\\main\\java\\repository\\ClientRepository.java", "source_location": "L45", "weight": 1.0}, {"source": "repository_clientrepository_clientrepository", "target": "repository_clientrepository_clientrepository_findallwithuninvoicedcompletedjobs", "relation": "method", "confidence": "EXTRACTED", "source_file": "C:\\Users\\VishalGoswami\\eclipse-workspace\\Sunny_Printers\\src\\main\\java\\repository\\ClientRepository.java", "source_location": "L74", "weight": 1.0}, {"source": "repository_clientrepository_clientrepository", "target": "repository_clientrepository_clientrepository_search", "relation": "method", "confidence": "EXTRACTED", "source_file": "C:\\Users\\VishalGoswami\\eclipse-workspace\\Sunny_Printers\\src\\main\\java\\repository\\ClientRepository.java", "source_location": "L101", "weight": 1.0}, {"source": "repository_clientrepository_clientrepository", "target": "repository_clientrepository_clientrepository_deletebyid", "relation": "method", "confidence": "EXTRACTED", "source_file": "C:\\Users\\VishalGoswami\\eclipse-workspace\\Sunny_Printers\\src\\main\\java\\repository\\ClientRepository.java", "source_location": "L138", "weight": 1.0}, {"source": "repository_clientrepository_clientrepository", "target": "repository_clientrepository_clientrepository_openeditclient", "relation": "method", "confidence": "EXTRACTED", "source_file": "C:\\Users\\VishalGoswami\\eclipse-workspace\\Sunny_Printers\\src\\main\\java\\repository\\ClientRepository.java", "source_location": "L155", "weight": 1.0}, {"source": "repository_clientrepository_clientrepository", "target": "repository_clientrepository_clientrepository_update", "relation": "method", "confidence": "EXTRACTED", "source_file": "C:\\Users\\VishalGoswami\\eclipse-workspace\\Sunny_Printers\\src\\main\\java\\repository\\ClientRepository.java", "source_location": "L161", "weight": 1.0}], "raw_calls": [{"caller_nid": "repository_clientrepository_clientrepository_save", "callee": "getConnection", "is_member_call": false, "source_file": "C:\\Users\\VishalGoswami\\eclipse-workspace\\Sunny_Printers\\src\\main\\java\\repository\\ClientRepository.java", "source_location": "L22"}, {"caller_nid": "repository_clientrepository_clientrepository_save", "callee": "prepareStatement", "is_member_call": false, "source_file": "C:\\Users\\VishalGoswami\\eclipse-workspace\\Sunny_Printers\\src\\main\\java\\repository\\ClientRepository.java", "source_location": "L23"}, {"caller_nid": "repository_clientrepository_clientrepository_save", "callee": "setString", "is_member_call": false, "source_file": "C:\\Users\\VishalGoswami\\eclipse-workspace\\Sunny_Printers\\src\\main\\java\\repository\\ClientRepository.java", "source_location": "L24"}, {"caller_nid": "repository_clientrepository_clientrepository_save", "callee": "getBusinessName", "is_member_call": false, "source_file": "C:\\Users\\VishalGoswami\\eclipse-workspace\\Sunny_Printers\\src\\main\\java\\repository\\ClientRepository.java", "source_location": "L24"}, {"caller_nid": "repository_clientrepository_clientrepository_save", "callee": "setString", "is_member_call": false, "source_file": "C:\\Users\\VishalGoswami\\eclipse-workspace\\Sunny_Printers\\src\\main\\java\\repository\\ClientRepository.java", "source_location": "L25"}, {"caller_nid": "repository_clientrepository_clientrepository_save", "callee": "getClientName", "is_member_call": false, "source_file": "C:\\Users\\VishalGoswami\\eclipse-workspace\\Sunny_Printers\\src\\main\\java\\repository\\ClientRepository.java", "source_location": "L25"}, {"caller_nid": "repository_clientrepository_clientrepository_save", "callee": "setString", "is_member_call": false, "source_file": "C:\\Users\\VishalGoswami\\eclipse-workspace\\Sunny_Printers\\src\\main\\java\\repository\\ClientRepository.java", "source_location": "L26"}, {"caller_nid": "repository_clientrepository_clientrepository_save", "callee": "getNickName", "is_member_call": false, "source_file": "C:\\Users\\VishalGoswami\\eclipse-workspace\\Sunny_Printers\\src\\main\\java\\repository\\ClientRepository.java", "source_location": "L26"}, {"caller_nid": "repository_clientrepository_clientrepository_save", "callee": "setString", "is_member_call": false, "source_file": "C:\\Users\\VishalGoswami\\eclipse-workspace\\Sunny_Printers\\src\\main\\java\\repository\\ClientRepository.java", "source_location": "L27"}, {"caller_nid": "repository_clientrepository_clientrepository_save", "callee": "getPhone", "is_member_call": false, "source_file": "C:\\Users\\VishalGoswami\\eclipse-workspace\\Sunny_Printers\\src\\main\\java\\repository\\ClientRepository.java", "source_location": "L27"}, {"caller_nid": "repository_clientrepository_clientrepository_save", "callee": "setString", "is_member_call": false, "source_file": "C:\\Users\\VishalGoswami\\eclipse-workspace\\Sunny_Printers\\src\\main\\java\\repository\\ClientRepository.java", "source_location": "L28"}, {"caller_nid": "repository_clientrepository_clientrepository_save", "callee": "getAltPhone", "is_member_call": false, "source_file": "C:\\Users\\VishalGoswami\\eclipse-workspace\\Sunny_Printers\\src\\main\\java\\repository\\ClientRepository.java", "source_location": "L28"}, {"caller_nid": "repository_clientrepository_clientrepository_save", "callee": "setString", "is_member_call": false, "source_file": "C:\\Users\\VishalGoswami\\eclipse-workspace\\Sunny_Printers\\src\\main\\java\\repository\\ClientRepository.java", "source_location": "L29"}, {"caller_nid": "repository_clientrepository_clientrepository_save", "callee": "getEmail", "is_member_call": false, "source_file": "C:\\Users\\VishalGoswami\\eclipse-workspace\\Sunny_Printers\\src\\main\\java\\repository\\ClientRepository.java", "source_location": "L29"}, {"caller_nid": "repository_clientrepository_clientrepository_save", "callee": "setString", "is_member_call": false, "source_file": "C:\\Users\\VishalGoswami\\eclipse-workspace\\Sunny_Printers\\src\\main\\java\\repository\\ClientRepository.java", "source_location": "L30"}, {"caller_nid": "repository_clientrepository_clientrepository_save", "callee": "getGst", "is_member_call": false, "source_file": "C:\\Users\\VishalGoswami\\eclipse-workspace\\Sunny_Printers\\src\\main\\java\\repository\\ClientRepository.java", "source_location": "L30"}, {"caller_nid": "repository_clientrepository_clientrepository_save", "callee": "setString", "is_member_call": false, "source_file": "C:\\Users\\VishalGoswami\\eclipse-workspace\\Sunny_Printers\\src\\main\\java\\repository\\ClientRepository.java", "source_location": "L31"}, {"caller_nid": "repository_clientrepository_clientrepository_save", "callee": "getPan", "is_member_call": false, "source_file": "C:\\Users\\VishalGoswami\\eclipse-workspace\\Sunny_Printers\\src\\main\\java\\repository\\ClientRepository.java", "source_location": "L31"}, {"caller_nid": "repository_clientrepository_clientrepository_save", "callee": "setString", "is_member_call": false, "source_file": "C:\\Users\\VishalGoswami\\eclipse-workspace\\Sunny_Printers\\src\\main\\java\\repository\\ClientRepository.java", "source_location": "L32"}, {"caller_nid": "repository_clientrepository_clientrepository_save", "callee": "getBillingAddress", "is_member_call": false, "source_file": "C:\\Users\\VishalGoswami\\eclipse-workspace\\Sunny_Printers\\src\\main\\java\\repository\\ClientRepository.java", "source_location": "L32"}, {"caller_nid": "repository_clientrepository_clientrepository_save", "callee": "setString", "is_member_call": false, "source_file": "C:\\Users\\VishalGoswami\\eclipse-workspace\\Sunny_Printers\\src\\main\\java\\repository\\ClientRepository.java", "source_location": "L33"}, {"caller_nid": "repository_clientrepository_clientrepository_save", "callee": "getShippingAddress", "is_member_call": false, "source_file": "C:\\Users\\VishalGoswami\\eclipse-workspace\\Sunny_Printers\\src\\main\\java\\repository\\ClientRepository.java", "source_location": "L33"}, {"caller_nid": "repository_clientrepository_clientrepository_save", "callee": "setString", "is_member_call": false, "source_file": "C:\\Users\\VishalGoswami\\eclipse-workspace\\Sunny_Printers\\src\\main\\java\\repository\\ClientRepository.java", "source_location": "L34"}, {"caller_nid": "repository_clientrepository_clientrepository_save", "callee": "getNotes", "is_member_call": false, "source_file": "C:\\Users\\VishalGoswami\\eclipse-workspace\\Sunny_Printers\\src\\main\\java\\repository\\ClientRepository.java", "source_location": "L34"}, {"caller_nid": "repository_clientrepository_clientrepository_save", "callee": "executeUpdate", "is_member_call": false, "source_file": "C:\\Users\\VishalGoswami\\eclipse-workspace\\Sunny_Printers\\src\\main\\java\\repository\\ClientRepository.java", "source_location": "L36"}, {"caller_nid": "repository_clientrepository_clientrepository_save", "callee": "printStackTrace", "is_member_call": false, "source_file": "C:\\Users\\VishalGoswami\\eclipse-workspace\\Sunny_Printers\\src\\main\\java\\repository\\ClientRepository.java", "source_location": "L39"}, {"caller_nid": "repository_clientrepository_clientrepository_findallsortedbyid", "callee": "getConnection", "is_member_call": false, "source_file": "C:\\Users\\VishalGoswami\\eclipse-workspace\\Sunny_Printers\\src\\main\\java\\repository\\ClientRepository.java", "source_location": "L50"}, {"caller_nid": "repository_clientrepository_clientrepository_findallsortedbyid", "callee": "prepareStatement", "is_member_call": false, "source_file": "C:\\Users\\VishalGoswami\\eclipse-workspace\\Sunny_Printers\\src\\main\\java\\repository\\ClientRepository.java", "source_location": "L51"}, {"caller_nid": "repository_clientrepository_clientrepository_findallsortedbyid", "callee": "executeQuery", "is_member_call": false, "source_file": "C:\\Users\\VishalGoswami\\eclipse-workspace\\Sunny_Printers\\src\\main\\java\\repository\\ClientRepository.java", "source_location": "L52"}, {"caller_nid": "repository_clientrepository_clientrepository_findallsortedbyid", "callee": "next", "is_member_call": false, "source_file": "C:\\Users\\VishalGoswami\\eclipse-workspace\\Sunny_Printers\\src\\main\\java\\repository\\ClientRepository.java", "source_location": "L54"}, {"caller_nid": "repository_clientrepository_clientrepository_findallsortedbyid", "callee": "getString", "is_member_call": false, "source_file": "C:\\Users\\VishalGoswami\\eclipse-workspace\\Sunny_Printers\\src\\main\\java\\repository\\ClientRepository.java", "source_location": "L55"}, {"caller_nid": "repository_clientrepository_clientrepository_findallsortedbyid", "callee": "getString", "is_member_call": false, "source_file": "C:\\Users\\VishalGoswami\\eclipse-workspace\\Sunny_Printers\\src\\main\\java\\repository\\ClientRepository.java", "source_location": "L55"}, {"caller_nid": "repository_clientrepository_clientrepository_findallsortedbyid", "callee": "getString", "is_member_call": false, "source_file": "C:\\Users\\VishalGoswami\\eclipse-workspace\\Sunny_Printers\\src\\main\\java\\repository\\ClientRepository.java", "source_location": "L56"}, {"caller_nid": "repository_clientrepository_clientrepository_findallsortedbyid", "callee": "getString", "is_member_call": false, "source_file": "C:\\Users\\VishalGoswami\\eclipse-workspace\\Sunny_Printers\\src\\main\\java\\repository\\ClientRepository.java", "source_location": "L56"}, {"caller_nid": "repository_clientrepository_clientrepository_findallsortedbyid", "callee": "getString", "is_member_call": false, "source_file": "C:\\Users\\VishalGoswami\\eclipse-workspace\\Sunny_Printers\\src\\main\\java\\repository\\ClientRepository.java", "source_location": "L56"}, {"caller_nid": "repository_clientrepository_clientrepository_findallsortedbyid", "callee": "getString", "is_member_call": false, "source_file": "C:\\Users\\VishalGoswami\\eclipse-workspace\\Sunny_Printers\\src\\main\\java\\repository\\ClientRepository.java", "source_location": "L57"}, {"caller_nid": "repository_clientrepository_clientrepository_findallsortedbyid", "callee": "getString", "is_member_call": false, "source_file": "C:\\Users\\VishalGoswami\\eclipse-workspace\\Sunny_Printers\\src\\main\\java\\repository\\ClientRepository.java", "source_location": "L57"}, {"caller_nid": "repository_clientrepository_clientrepository_findallsortedbyid", "callee": "getString", "is_member_call": false, "source_file": "C:\\Users\\VishalGoswami\\eclipse-workspace\\Sunny_Printers\\src\\main\\java\\repository\\ClientRepository.java", "source_location": "L57"}, {"caller_nid": "repository_clientrepository_clientrepository_findallsortedbyid", "callee": "getString", "is_member_call": false, "source_file": "C:\\Users\\VishalGoswami\\eclipse-workspace\\Sunny_Printers\\src\\main\\java\\repository\\ClientRepository.java", "source_location": "L58"}, {"caller_nid": "repository_clientrepository_clientrepository_findallsortedbyid", "callee": "getString", "is_member_call": false, "source_file": "C:\\Users\\VishalGoswami\\eclipse-workspace\\Sunny_Printers\\src\\main\\java\\repository\\ClientRepository.java", "source_location": "L58"}, {"caller_nid": "repository_clientrepository_clientrepository_findallsortedbyid", "callee": "getString", "is_member_call": false, "source_file": "C:\\Users\\VishalGoswami\\eclipse-workspace\\Sunny_Printers\\src\\main\\java\\repository\\ClientRepository.java", "source_location": "L58"}, {"caller_nid": "repository_clientrepository_clientrepository_findallsortedbyid", "callee": "setId", "is_member_call": false, "source_file": "C:\\Users\\VishalGoswami\\eclipse-workspace\\Sunny_Printers\\src\\main\\java\\repository\\ClientRepository.java", "source_location": "L59"}, {"caller_nid": "repository_clientrepository_clientrepository_findallsortedbyid", "callee": "getInt", "is_member_call": false, "source_file": "C:\\Users\\VishalGoswami\\eclipse-workspace\\Sunny_Printers\\src\\main\\java\\repository\\ClientRepository.java", "source_location": "L59"}, {"caller_nid": "repository_clientrepository_clientrepository_findallsortedbyid", "callee": "add", "is_member_call": false, "source_file": "C:\\Users\\VishalGoswami\\eclipse-workspace\\Sunny_Printers\\src\\main\\java\\repository\\ClientRepository.java", "source_location": "L60"}, {"caller_nid": "repository_clientrepository_clientrepository_findallsortedbyid", "callee": "printStackTrace", "is_member_call": false, "source_file": "C:\\Users\\VishalGoswami\\eclipse-workspace\\Sunny_Printers\\src\\main\\java\\repository\\ClientRepository.java", "source_location": "L64"}, {"caller_nid": "repository_clientrepository_clientrepository_findallwithuninvoicedcompletedjobs", "callee": "getConnection", "is_member_call": false, "source_file": "C:\\Users\\VishalGoswami\\eclipse-workspace\\Sunny_Printers\\src\\main\\java\\repository\\ClientRepository.java", "source_location": "L84"}, {"caller_nid": "repository_clientrepository_clientrepository_findallwithuninvoicedcompletedjobs", "callee": "prepareStatement", "is_member_call": false, "source_file": "C:\\Users\\VishalGoswami\\eclipse-workspace\\Sunny_Printers\\src\\main\\java\\repository\\ClientRepository.java", "source_location": "L85"}, {"caller_nid": "repository_clientrepository_clientrepository_findallwithuninvoicedcompletedjobs", "callee": "executeQuery", "is_member_call": false, "source_file": "C:\\Users\\VishalGoswami\\eclipse-workspace\\Sunny_Printers\\src\\main\\java\\repository\\ClientRepository.java", "source_location": "L86"}, {"caller_nid": "repository_clientrepository_clientrepository_findallwithuninvoicedcompletedjobs", "callee": "next", "is_member_call": false, "source_file": "C:\\Users\\VishalGoswami\\eclipse-workspace\\Sunny_Printers\\src\\main\\java\\repository\\ClientRepository.java", "source_location": "L87"}, {"caller_nid": "repository_clientrepository_clientrepository_findallwithuninvoicedcompletedjobs", "callee": "getString", "is_member_call": false, "source_file": "C:\\Users\\VishalGoswami\\eclipse-workspace\\Sunny_Printers\\src\\main\\java\\repository\\ClientRepository.java", "source_location": "L88"}, {"caller_nid": "repository_clientrepository_clientrepository_findallwithuninvoicedcompletedjobs", "callee": "getString", "is_member_call": false, "source_file": "C:\\Users\\VishalGoswami\\eclipse-workspace\\Sunny_Printers\\src\\main\\java\\repository\\ClientRepository.java", "source_location": "L88"}, {"caller_nid": "repository_clientrepository_clientrepository_findallwithuninvoicedcompletedjobs", "callee": "getString", "is_member_call": false, "source_file": "C:\\Users\\VishalGoswami\\eclipse-workspace\\Sunny_Printers\\src\\main\\java\\repository\\ClientRepository.java", "source_location": "L89"}, {"caller_nid": "repository_clientrepository_clientrepository_findallwithuninvoicedcompletedjobs", "callee": "getString", "is_member_call": false, "source_file": "C:\\Users\\VishalGoswami\\eclipse-workspace\\Sunny_Printers\\src\\main\\java\\repository\\ClientRepository.java", "source_location": "L89"}, {"caller_nid": "repository_clientrepository_clientrepository_findallwithuninvoicedcompletedjobs", "callee": "getString", "is_member_call": false, "source_file": "C:\\Users\\VishalGoswami\\eclipse-workspace\\Sunny_Printers\\src\\main\\java\\repository\\ClientRepository.java", "source_location": "L89"}, {"caller_nid": "repository_clientrepository_clientrepository_findallwithuninvoicedcompletedjobs", "callee": "getString", "is_member_call": false, "source_file": "C:\\Users\\VishalGoswami\\eclipse-workspace\\Sunny_Printers\\src\\main\\java\\repository\\ClientRepository.java", "source_location": "L90"}, {"caller_nid": "repository_clientrepository_clientrepository_findallwithuninvoicedcompletedjobs", "callee": "getString", "is_member_call": false, "source_file": "C:\\Users\\VishalGoswami\\eclipse-workspace\\Sunny_Printers\\src\\main\\java\\repository\\ClientRepository.java", "source_location": "L90"}, {"caller_nid": "repository_clientrepository_clientrepository_findallwithuninvoicedcompletedjobs", "callee": "getString", "is_member_call": false, "source_file": "C:\\Users\\VishalGoswami\\eclipse-workspace\\Sunny_Printers\\src\\main\\java\\repository\\ClientRepository.java", "source_location": "L90"}, {"caller_nid": "repository_clientrepository_clientrepository_findallwithuninvoicedcompletedjobs", "callee": "getString", "is_member_call": false, "source_file": "C:\\Users\\VishalGoswami\\eclipse-workspace\\Sunny_Printers\\src\\main\\java\\repository\\ClientRepository.java", "source_location": "L91"}, {"caller_nid": "repository_clientrepository_clientrepository_findallwithuninvoicedcompletedjobs", "callee": "getString", "is_member_call": false, "source_file": "C:\\Users\\VishalGoswami\\eclipse-workspace\\Sunny_Printers\\src\\main\\java\\repository\\ClientRepository.java", "source_location": "L91"}, {"caller_nid": "repository_clientrepository_clientrepository_findallwithuninvoicedcompletedjobs", "callee": "getString", "is_member_call": false, "source_file": "C:\\Users\\VishalGoswami\\eclipse-workspace\\Sunny_Printers\\src\\main\\java\\repository\\ClientRepository.java", "source_location": "L91"}, {"caller_nid": "repository_clientrepository_clientrepository_findallwithuninvoicedcompletedjobs", "callee": "setId", "is_member_call": false, "source_file": "C:\\Users\\VishalGoswami\\eclipse-workspace\\Sunny_Printers\\src\\main\\java\\repository\\ClientRepository.java", "source_location": "L92"}, {"caller_nid": "repository_clientrepository_clientrepository_findallwithuninvoicedcompletedjobs", "callee": "getInt", "is_member_call": false, "source_file": "C:\\Users\\VishalGoswami\\eclipse-workspace\\Sunny_Printers\\src\\main\\java\\repository\\ClientRepository.java", "source_location": "L92"}, {"caller_nid": "repository_clientrepository_clientrepository_findallwithuninvoicedcompletedjobs", "callee": "add", "is_member_call": false, "source_file": "C:\\Users\\VishalGoswami\\eclipse-workspace\\Sunny_Printers\\src\\main\\java\\repository\\ClientRepository.java", "source_location": "L93"}, {"caller_nid": "repository_clientrepository_clientrepository_findallwithuninvoicedcompletedjobs", "callee": "printStackTrace", "is_member_call": false, "source_file": "C:\\Users\\VishalGoswami\\eclipse-workspace\\Sunny_Printers\\src\\main\\java\\repository\\ClientRepository.java", "source_location": "L96"}, {"caller_nid": "repository_clientrepository_clientrepository_search", "callee": "getConnection", "is_member_call": false, "source_file": "C:\\Users\\VishalGoswami\\eclipse-workspace\\Sunny_Printers\\src\\main\\java\\repository\\ClientRepository.java", "source_location": "L110"}, {"caller_nid": "repository_clientrepository_clientrepository_search", "callee": "prepareStatement", "is_member_call": false, "source_file": "C:\\Users\\VishalGoswami\\eclipse-workspace\\Sunny_Printers\\src\\main\\java\\repository\\ClientRepository.java", "source_location": "L110"}, {"caller_nid": "repository_clientrepository_clientrepository_search", "callee": "setString", "is_member_call": false, "source_file": "C:\\Users\\VishalGoswami\\eclipse-workspace\\Sunny_Printers\\src\\main\\java\\repository\\ClientRepository.java", "source_location": "L115"}, {"caller_nid": "repository_clientrepository_clientrepository_search", "callee": "executeQuery", "is_member_call": false, "source_file": "C:\\Users\\VishalGoswami\\eclipse-workspace\\Sunny_Printers\\src\\main\\java\\repository\\ClientRepository.java", "source_location": "L118"}, {"caller_nid": "repository_clientrepository_clientrepository_search", "callee": "next", "is_member_call": false, "source_file": "C:\\Users\\VishalGoswami\\eclipse-workspace\\Sunny_Printers\\src\\main\\java\\repository\\ClientRepository.java", "source_location": "L120"}, {"caller_nid": "repository_clientrepository_clientrepository_search", "callee": "getString", "is_member_call": false, "source_file": "C:\\Users\\VishalGoswami\\eclipse-workspace\\Sunny_Printers\\src\\main\\java\\repository\\ClientRepository.java", "source_location": "L122"}, {"caller_nid": "repository_clientrepository_clientrepository_search", "callee": "getString", "is_member_call": false, "source_file": "C:\\Users\\VishalGoswami\\eclipse-workspace\\Sunny_Printers\\src\\main\\java\\repository\\ClientRepository.java", "source_location": "L122"}, {"caller_nid": "repository_clientrepository_clientrepository_search", "callee": "getString", "is_member_call": false, "source_file": "C:\\Users\\VishalGoswami\\eclipse-workspace\\Sunny_Printers\\src\\main\\java\\repository\\ClientRepository.java", "source_location": "L123"}, {"caller_nid": "repository_clientrepository_clientrepository_search", "callee": "getString", "is_member_call": false, "source_file": "C:\\Users\\VishalGoswami\\eclipse-workspace\\Sunny_Printers\\src\\main\\java\\repository\\ClientRepository.java", "source_location": "L123"}, {"caller_nid": "repository_clientrepository_clientrepository_search", "callee": "getString", "is_member_call": false, "source_file": "C:\\Users\\VishalGoswami\\eclipse-workspace\\Sunny_Printers\\src\\main\\java\\repository\\ClientRepository.java", "source_location": "L123"}, {"caller_nid": "repository_clientrepository_clientrepository_search", "callee": "getString", "is_member_call": false, "source_file": "C:\\Users\\VishalGoswami\\eclipse-workspace\\Sunny_Printers\\src\\main\\java\\repository\\ClientRepository.java", "source_location": "L124"}, {"caller_nid": "repository_clientrepository_clientrepository_search", "callee": "getString", "is_member_call": false, "source_file": "C:\\Users\\VishalGoswami\\eclipse-workspace\\Sunny_Printers\\src\\main\\java\\repository\\ClientRepository.java", "source_location": "L124"}, {"caller_nid": "repository_clientrepository_clientrepository_search", "callee": "getString", "is_member_call": false, "source_file": "C:\\Users\\VishalGoswami\\eclipse-workspace\\Sunny_Printers\\src\\main\\java\\repository\\ClientRepository.java", "source_location": "L124"}, {"caller_nid": "repository_clientrepository_clientrepository_search", "callee": "getString", "is_member_call": false, "source_file": "C:\\Users\\VishalGoswami\\eclipse-workspace\\Sunny_Printers\\src\\main\\java\\repository\\ClientRepository.java", "source_location": "L125"}, {"caller_nid": "repository_clientrepository_clientrepository_search", "callee": "getString", "is_member_call": false, "source_file": "C:\\Users\\VishalGoswami\\eclipse-workspace\\Sunny_Printers\\src\\main\\java\\repository\\ClientRepository.java", "source_location": "L125"}, {"caller_nid": "repository_clientrepository_clientrepository_search", "callee": "getString", "is_member_call": false, "source_file": "C:\\Users\\VishalGoswami\\eclipse-workspace\\Sunny_Printers\\src\\main\\java\\repository\\ClientRepository.java", "source_location": "L125"}, {"caller_nid": "repository_clientrepository_clientrepository_search", "callee": "setId", "is_member_call": false, "source_file": "C:\\Users\\VishalGoswami\\eclipse-workspace\\Sunny_Printers\\src\\main\\java\\repository\\ClientRepository.java", "source_location": "L127"}, {"caller_nid": "repository_clientrepository_clientrepository_search", "callee": "getInt", "is_member_call": false, "source_file": "C:\\Users\\VishalGoswami\\eclipse-workspace\\Sunny_Printers\\src\\main\\java\\repository\\ClientRepository.java", "source_location": "L127"}, {"caller_nid": "repository_clientrepository_clientrepository_search", "callee": "add", "is_member_call": false, "source_file": "C:\\Users\\VishalGoswami\\eclipse-workspace\\Sunny_Printers\\src\\main\\java\\repository\\ClientRepository.java", "source_location": "L128"}, {"caller_nid": "repository_clientrepository_clientrepository_search", "callee": "printStackTrace", "is_member_call": false, "source_file": "C:\\Users\\VishalGoswami\\eclipse-workspace\\Sunny_Printers\\src\\main\\java\\repository\\ClientRepository.java", "source_location": "L132"}, {"caller_nid": "repository_clientrepository_clientrepository_deletebyid", "callee": "getConnection", "is_member_call": false, "source_file": "C:\\Users\\VishalGoswami\\eclipse-workspace\\Sunny_Printers\\src\\main\\java\\repository\\ClientRepository.java", "source_location": "L142"}, {"caller_nid": "repository_clientrepository_clientrepository_deletebyid", "callee": "prepareStatement", "is_member_call": false, "source_file": "C:\\Users\\VishalGoswami\\eclipse-workspace\\Sunny_Printers\\src\\main\\java\\repository\\ClientRepository.java", "source_location": "L142"}, {"caller_nid": "repository_clientrepository_clientrepository_deletebyid", "callee": "setInt", "is_member_call": false, "source_file": "C:\\Users\\VishalGoswami\\eclipse-workspace\\Sunny_Printers\\src\\main\\java\\repository\\ClientRepository.java", "source_location": "L144"}, {"caller_nid": "repository_clientrepository_clientrepository_deletebyid", "callee": "executeUpdate", "is_member_call": false, "source_file": "C:\\Users\\VishalGoswami\\eclipse-workspace\\Sunny_Printers\\src\\main\\java\\repository\\ClientRepository.java", "source_location": "L146"}, {"caller_nid": "repository_clientrepository_clientrepository_deletebyid", "callee": "printStackTrace", "is_member_call": false, "source_file": "C:\\Users\\VishalGoswami\\eclipse-workspace\\Sunny_Printers\\src\\main\\java\\repository\\ClientRepository.java", "source_location": "L149"}, {"caller_nid": "repository_clientrepository_clientrepository_openeditclient", "callee": "println", "is_member_call": false, "source_file": "C:\\Users\\VishalGoswami\\eclipse-workspace\\Sunny_Printers\\src\\main\\java\\repository\\ClientRepository.java", "source_location": "L156"}, {"caller_nid": "repository_clientrepository_clientrepository_openeditclient", "callee": "getId", "is_member_call": false, "source_file": "C:\\Users\\VishalGoswami\\eclipse-workspace\\Sunny_Printers\\src\\main\\java\\repository\\ClientRepository.java", "source_location": "L156"}, {"caller_nid": "repository_clientrepository_clientrepository_update", "callee": "getConnection", "is_member_call": false, "source_file": "C:\\Users\\VishalGoswami\\eclipse-workspace\\Sunny_Printers\\src\\main\\java\\repository\\ClientRepository.java", "source_location": "L164"}, {"caller_nid": "repository_clientrepository_clientrepository_update", "callee": "prepareStatement", "is_member_call": false, "source_file": "C:\\Users\\VishalGoswami\\eclipse-workspace\\Sunny_Printers\\src\\main\\java\\repository\\ClientRepository.java", "source_location": "L164"}, {"caller_nid": "repository_clientrepository_clientrepository_update", "callee": "setString", "is_member_call": false, "source_file": "C:\\Users\\VishalGoswami\\eclipse-workspace\\Sunny_Printers\\src\\main\\java\\repository\\ClientRepository.java", "source_location": "L166"}, {"caller_nid": "repository_clientrepository_clientrepository_update", "callee": "getBusinessName", "is_member_call": false, "source_file": "C:\\Users\\VishalGoswami\\eclipse-workspace\\Sunny_Printers\\src\\main\\java\\repository\\ClientRepository.java", "source_location": "L166"}, {"caller_nid": "repository_clientrepository_clientrepository_update", "callee": "setString", "is_member_call": false, "source_file": "C:\\Users\\VishalGoswami\\eclipse-workspace\\Sunny_Printers\\src\\main\\java\\repository\\ClientRepository.java", "source_location": "L167"}, {"caller_nid": "repository_clientrepository_clientrepository_update", "callee": "getClientName", "is_member_call": false, "source_file": "C:\\Users\\VishalGoswami\\eclipse-workspace\\Sunny_Printers\\src\\main\\java\\repository\\ClientRepository.java", "source_location": "L167"}, {"caller_nid": "repository_clientrepository_clientrepository_update", "callee": "setString", "is_member_call": false, "source_file": "C:\\Users\\VishalGoswami\\eclipse-workspace\\Sunny_Printers\\src\\main\\java\\repository\\ClientRepository.java", "source_location": "L168"}, {"caller_nid": "repository_clientrepository_clientrepository_update", "callee": "getNickName", "is_member_call": false, "source_file": "C:\\Users\\VishalGoswami\\eclipse-workspace\\Sunny_Printers\\src\\main\\java\\repository\\ClientRepository.java", "source_location": "L168"}, {"caller_nid": "repository_clientrepository_clientrepository_update", "callee": "setString", "is_member_call": false, "source_file": "C:\\Users\\VishalGoswami\\eclipse-workspace\\Sunny_Printers\\src\\main\\java\\repository\\ClientRepository.java", "source_location": "L169"}, {"caller_nid": "repository_clientrepository_clientrepository_update", "callee": "getPhone", "is_member_call": false, "source_file": "C:\\Users\\VishalGoswami\\eclipse-workspace\\Sunny_Printers\\src\\main\\java\\repository\\ClientRepository.java", "source_location": "L169"}, {"caller_nid": "repository_clientrepository_clientrepository_update", "callee": "setString", "is_member_call": false, "source_file": "C:\\Users\\VishalGoswami\\eclipse-workspace\\Sunny_Printers\\src\\main\\java\\repository\\ClientRepository.java", "source_location": "L170"}, {"caller_nid": "repository_clientrepository_clientrepository_update", "callee": "getAltPhone", "is_member_call": false, "source_file": "C:\\Users\\VishalGoswami\\eclipse-workspace\\Sunny_Printers\\src\\main\\java\\repository\\ClientRepository.java", "source_location": "L170"}, {"caller_nid": "repository_clientrepository_clientrepository_update", "callee": "setString", "is_member_call": false, "source_file": "C:\\Users\\VishalGoswami\\eclipse-workspace\\Sunny_Printers\\src\\main\\java\\repository\\ClientRepository.java", "source_location": "L171"}, {"caller_nid": "repository_clientrepository_clientrepository_update", "callee": "getEmail", "is_member_call": false, "source_file": "C:\\Users\\VishalGoswami\\eclipse-workspace\\Sunny_Printers\\src\\main\\java\\repository\\ClientRepository.java", "source_location": "L171"}, {"caller_nid": "repository_clientrepository_clientrepository_update", "callee": "setString", "is_member_call": false, "source_file": "C:\\Users\\VishalGoswami\\eclipse-workspace\\Sunny_Printers\\src\\main\\java\\repository\\ClientRepository.java", "source_location": "L172"}, {"caller_nid": "repository_clientrepository_clientrepository_update", "callee": "getGst", "is_member_call": false, "source_file": "C:\\Users\\VishalGoswami\\eclipse-workspace\\Sunny_Printers\\src\\main\\java\\repository\\ClientRepository.java", "source_location": "L172"}, {"caller_nid": "repository_clientrepository_clientrepository_update", "callee": "setString", "is_member_call": false, "source_file": "C:\\Users\\VishalGoswami\\eclipse-workspace\\Sunny_Printers\\src\\main\\java\\repository\\ClientRepository.java", "source_location": "L173"}, {"caller_nid": "repository_clientrepository_clientrepository_update", "callee": "getPan", "is_member_call": false, "source_file": "C:\\Users\\VishalGoswami\\eclipse-workspace\\Sunny_Printers\\src\\main\\java\\repository\\ClientRepository.java", "source_location": "L173"}, {"caller_nid": "repository_clientrepository_clientrepository_update", "callee": "setString", "is_member_call": false, "source_file": "C:\\Users\\VishalGoswami\\eclipse-workspace\\Sunny_Printers\\src\\main\\java\\repository\\ClientRepository.java", "source_location": "L174"}, {"caller_nid": "repository_clientrepository_clientrepository_update", "callee": "getBillingAddress", "is_member_call": false, "source_file": "C:\\Users\\VishalGoswami\\eclipse-workspace\\Sunny_Printers\\src\\main\\java\\repository\\ClientRepository.java", "source_location": "L174"}, {"caller_nid": "repository_clientrepository_clientrepository_update", "callee": "setString", "is_member_call": false, "source_file": "C:\\Users\\VishalGoswami\\eclipse-workspace\\Sunny_Printers\\src\\main\\java\\repository\\ClientRepository.java", "source_location": "L175"}, {"caller_nid": "repository_clientrepository_clientrepository_update", "callee": "getShippingAddress", "is_member_call": false, "source_file": "C:\\Users\\VishalGoswami\\eclipse-workspace\\Sunny_Printers\\src\\main\\java\\repository\\ClientRepository.java", "source_location": "L175"}, {"caller_nid": "repository_clientrepository_clientrepository_update", "callee": "setString", "is_member_call": false, "source_file": "C:\\Users\\VishalGoswami\\eclipse-workspace\\Sunny_Printers\\src\\main\\java\\repository\\ClientRepository.java", "source_location": "L176"}, {"caller_nid": "repository_clientrepository_clientrepository_update", "callee": "getNotes", "is_member_call": false, "source_file": "C:\\Users\\VishalGoswami\\eclipse-workspace\\Sunny_Printers\\src\\main\\java\\repository\\ClientRepository.java", "source_location": "L176"}, {"caller_nid": "repository_clientrepository_clientrepository_update", "callee": "setInt", "is_member_call": false, "source_file": "C:\\Users\\VishalGoswami\\eclipse-workspace\\Sunny_Printers\\src\\main\\java\\repository\\ClientRepository.java", "source_location": "L177"}, {"caller_nid": "repository_clientrepository_clientrepository_update", "callee": "getId", "is_member_call": false, "source_file": "C:\\Users\\VishalGoswami\\eclipse-workspace\\Sunny_Printers\\src\\main\\java\\repository\\ClientRepository.java", "source_location": "L177"}, {"caller_nid": "repository_clientrepository_clientrepository_update", "callee": "executeUpdate", "is_member_call": false, "source_file": "C:\\Users\\VishalGoswami\\eclipse-workspace\\Sunny_Printers\\src\\main\\java\\repository\\ClientRepository.java", "source_location": "L179"}, {"caller_nid": "repository_clientrepository_clientrepository_update", "callee": "printStackTrace", "is_member_call": false, "source_file": "C:\\Users\\VishalGoswami\\eclipse-workspace\\Sunny_Printers\\src\\main\\java\\repository\\ClientRepository.java", "source_location": "L182"}]}